{"tr626/kick":{"name":"TR-626 kick","pack":"tr626","oscs":[{"wave":0,"freq":"64,0,0,0,1.1","bp1":"0,1,20,0,1,0","bp0":"0,1,240,0,20,0","amp":"1,0,1,1"}]},"tr626/snare":{"name":"TR-626 snare","pack":"tr626","oscs":[{"wave":0,"freq":"225,0,0,0,0.4","bp1":"0,1,16,0,1,0","bp0":"0,1,90,0,20,0","amp":"0.55,0,1,1"},{"wave":5,"bp0":"0,1,160,0,15,0","amp":"0.95,0,1,1","filter_type":3,"filter_freq":"2000"}]},"tr626/rim":{"name":"TR-626 rim","pack":"tr626","oscs":[{"wave":0,"freq":"2050,0,0,0,0","bp1":"0,1,1,0,1,0","bp0":"0,1,18,0,20,0","amp":"0.65,0,1,1"}]},"tr626/clap":{"name":"TR-626 clap","pack":"tr626","oscs":[{"wave":5,"bp0":"0,1,10,0.5,20,0.95,31,0.4,44,0.8,250,0,20,0","amp":"0.95,0,1,1","filter_type":2,"filter_freq":"1380","resonance":"2"}]},"tr626/chh":{"name":"TR-626 chh","pack":"tr626","oscs":[{"wave":5,"bp0":"0,1,34,0,15,0","amp":"0.8,0,1,1","filter_type":3,"filter_freq":"9000"}]},"tr626/ohh":{"name":"TR-626 ohh","pack":"tr626","oscs":[{"wave":5,"bp0":"0,1,90,0.4,360,0,25,0","amp":"0.8,0,1,1","filter_type":3,"filter_freq":"8400"}]},"tr626/tomlo":{"name":"TR-626 tomlo","pack":"tr626","oscs":[{"wave":0,"freq":"100,0,0,0,0.7","bp1":"0,1,62,0,1,0","bp0":"0,1,240,0,20,0","amp":"0.88,0,1,1"}]},"tr626/tommid":{"name":"TR-626 tommid","pack":"tr626","oscs":[{"wave":0,"freq":"145,0,0,0,0.7","bp1":"0,1,55,0,1,0","bp0":"0,1,215,0,20,0","amp":"0.88,0,1,1"}]},"tr626/tomhi":{"name":"TR-626 tomhi","pack":"tr626","oscs":[{"wave":0,"freq":"195,0,0,0,0.7","bp1":"0,1,48,0,1,0","bp0":"0,1,190,0,20,0","amp":"0.88,0,1,1"}]},"tr626/ride":{"name":"TR-626 ride","pack":"tr626","oscs":[{"wave":5,"bp0":"0,0.8,230,0.35,1100,0,40,0","amp":"0.5,0,1,1","filter_type":3,"filter_freq":"8800"}]},"tr626/crash":{"name":"TR-626 crash","pack":"tr626","oscs":[{"wave":5,"bp0":"0,1,310,0.4,1400,0,40,0","amp":"0.75,0,1,1","filter_type":3,"filter_freq":"5700"}]},"tr626/shaker":{"name":"TR-626 shaker","pack":"tr626","oscs":[{"wave":5,"bp0":"0,0.4,14,1,78,0,15,0","amp":"0.55,0,1,1","filter_type":3,"filter_freq":"9200"}]},"tr626/congahi":{"name":"TR-626 congahi","pack":"tr626","oscs":[{"wave":0,"freq":"375,0,0,0,0.3","bp1":"0,1,22,0,1,0","bp0":"0,1,155,0,20,0","amp":"0.82,0,1,1"}]},"tr626/congalo":{"name":"TR-626 congalo","pack":"tr626","oscs":[{"wave":0,"freq":"228,0,0,0,0.3","bp1":"0,1,26,0,1,0","bp0":"0,1,185,0,20,0","amp":"0.82,0,1,1"}]}}